{
  "db_name": "PostgreSQL",
  "query": "\n            INSERT INTO config_variable_set_entries (\n                entry_id,\n                resource_uid,\n                resource_generation,\n                account_id,\n                variable_key,\n                value,\n                created_at,\n                updated_at\n            )\n            SELECT e.entry_id, $1, $2, e.account_id, e.variable_key, e.value, e.created_at, e.updated_at\n            FROM UNNEST($3::uuid[], $4::text[], $5::text[], $6::text[], $7::timestamptz[], $8::timestamptz[])\n                AS e(entry_id, account_id, variable_key, value, created_at, updated_at)\n            ",
  "describe": {
    "columns": [],
    "parameters": {
      "Left": [
        "Uuid",
        "Int8",
        "UuidArray",
        "TextArray",
        "TextArray",
        "TextArray",
        "TimestamptzArray",
        "TimestamptzArray"
      ]
    },
    "nullable": []
  },
  "hash": "4ea061c24a262cacc2ee1eb12d8ed4403c5ae4e00a207f62546d675662bded99"
}
